{
  "id": "319c0489-7eab-4bef-9771-02e9bec4ecbc",
  "type": "api_contract",
  "title": "Landmark retrieval endpoint",
  "description": "API endpoint for retrieving landmarks",
  "file_path": "/Users/cskoons/projects/github/Tekton/landmarks/test_landmark_system.py",
  "line_number": 58,
  "timestamp": "2025-06-21T19:08:23.812975",
  "author": "system",
  "metadata": {
    "endpoint": "/api/landmarks/{id}",
    "method": "GET",
    "request_schema": {},
    "response_schema": {
      "id": "string",
      "type": "string",
      "title": "string"
    },
    "auth_required": false
  },
  "tags": [],
  "related_landmarks": []
}