{
  "id": "adc5d8cf-a911-47e3-b068-04300b4b35fd",
  "type": "architecture_decision",
  "title": "Unified UI server architecture",
  "description": "Hephaestus UI server component managing both HTTP/WebSocket and MCP servers.",
  "file_path": "/Users/cskoons/projects/github/Tekton/Hephaestus/hephaestus/core/hephaestus_component.py",
  "line_number": 16,
  "timestamp": "2025-06-21T20:11:21.208494",
  "author": "system",
  "metadata": {
    "rationale": "Single component managing both HTTP/WebSocket UI server and MCP DevTools for centralized UI operations",
    "alternatives_considered": [
      "Separate UI and DevTools components",
      "Client-side only UI",
      "Multiple UI servers"
    ],
    "impacts": [],
    "decided_by": "team"
  },
  "tags": [],
  "related_landmarks": []
}